lijunshi_demo/__init__.py
lijunshi_demo/server.py
lijunshi_demo-0.1.0.dist-info/METADATA
lijunshi_demo-0.1.0.dist-info/WHEEL
lijunshi_demo-0.1.0.dist-info/entry_points.txt
lijunshi_demo-0.1.0.dist-info/RECORD
