Metadata-Version: 2.4
Name: lijunshi-demo
Version: 0.1.0
Summary: lijunshi demo pack
Author-email: lijunshi <lijunshi2015@163.com>
Requires-Python: >=3.11
Requires-Dist: mcp>=1.6.0
